roundtripini.py
roundtripini-0.4.1.dist-info/LICENSE
roundtripini-0.4.1.dist-info/METADATA
roundtripini-0.4.1.dist-info/WHEEL
roundtripini-0.4.1.dist-info/top_level.txt
roundtripini-0.4.1.dist-info/RECORD
